[
  {
    "changeuuid": "961d0d6f-0601-11e8-ae97-52543be04c81",
    "stationuuid": "961d0d6b-0601-11e8-ae97-52543be04c81",
    "name": "HJ94.1 Boom FM Georgetown",
    "url": "http://192.99.8.192:3630/stream",
    "url_resolved": "http://192.99.8.192:3630/stream",
    "homepage": "http://www.hj941.com/",
    "favicon": "http://www.hj941.com/images/logo.png",
    "tags": "bollywood,caribbean music,local music",
    "country": "Guyana",
    "countrycode": "GY",
    "state": "",
    "language": "english",
    "votes": 70,
    "lastchangetime": "2020-01-23 20:40:48",
    "codec": "MP3",
    "bitrate": 192,
    "hls": 0,
    "lastcheckok": 1,
    "lastchecktime": "2020-09-03 07:24:57",
    "lastcheckoktime": "2020-09-03 07:24:57",
    "lastlocalchecktime": "2020-09-02 16:34:27",
    "clicktimestamp": "2020-09-03 00:16:39",
    "clickcount": 53,
    "clicktrend": -2
  },
  {
    "changeuuid": "9646c529-0601-11e8-ae97-52543be04c81",
    "stationuuid": "9646c527-0601-11e8-ae97-52543be04c81",
    "name": "Mix 90.1 Georgetown",
    "url": "http://media.guardian.co.tt:8000/iradiogy",
    "url_resolved": "http://media.guardian.co.tt:8000/iradiogy",
    "homepage": "http://www.mix901fm.com/",
    "favicon": "http://www.iradiogy.com/wp-content/uploads/2015/11/cropped-logo.png",
    "tags": "contemporary hits,georgetown",
    "country": "Guyana",
    "countrycode": "GY",
    "state": "",
    "language": "english",
    "votes": 34,
    "lastchangetime": "2020-01-23 20:40:49",
    "codec": "MP3",
    "bitrate": 128,
    "hls": 0,
    "lastcheckok": 0,
    "lastchecktime": "2020-09-03 00:56:39",
    "lastcheckoktime": "2020-09-01 16:59:59",
    "lastlocalchecktime": "2020-09-02 17:14:26",
    "clicktimestamp": "2020-09-01 23:55:51",
    "clickcount": 22,
    "clicktrend": -2
  },
  {
    "changeuuid": "96486b08-0601-11e8-ae97-52543be04c81",
    "stationuuid": "96486b05-0601-11e8-ae97-52543be04c81",
    "name": "NTN Radio 89.1 Georgetown",
    "url": "http://auds1.intacs.com/ntnradio",
    "url_resolved": "http://auds1.intacs.com/ntnradio",
    "homepage": "http://ntntv-radio.com/",
    "favicon": "http://ntntv-radio.com/wp-content/uploads/2013/02/favicon.png",
    "tags": "south asian music,bollywood,georgetown",
    "country": "Guyana",
    "countrycode": "GY",
    "state": "",
    "language": "english",
    "votes": 47,
    "lastchangetime": "2020-01-23 20:40:49",
    "codec": "MP3",
    "bitrate": 128,
    "hls": 0,
    "lastcheckok": 1,
    "lastchecktime": "2020-09-03 00:56:39",
    "lastcheckoktime": "2020-09-03 00:56:39",
    "lastlocalchecktime": "2020-09-02 23:05:04",
    "clicktimestamp": "2020-09-01 23:55:35",
    "clickcount": 19,
    "clicktrend": -1
  }
]

